miniloop.cp313-win_amd64.pyd
miniloop-1.0.2.dist-info/licenses/LICENSE
miniloop-1.0.2.dist-info/METADATA
miniloop-1.0.2.dist-info/WHEEL
miniloop-1.0.2.dist-info/top_level.txt
miniloop-1.0.2.dist-info/RECORD
