Metadata-Version: 2.4
Name: miniloop
Version: 1.0.2
Summary: MiniLoop is a lightweight Python game loop library designed to provide a simple and efficient way to manage update and render cycles in real-time applications.
Home-page: https://github.com/Sekiraw/MiniLoop
Author: Qiyaya
Author-email: v2020.bohus.peter@gmail.com
License: Apache-2.0
Keywords: GAME,LOOP,PYGAME,RENDER,CYCLE
Classifier: Development Status :: 4 - Beta
Classifier: Intended Audience :: Developers
Classifier: Topic :: Software Development :: Build Tools
Classifier: License :: OSI Approved :: Apache Software License
Classifier: Programming Language :: Python :: 3.7
Classifier: Programming Language :: Python :: 3.8
Classifier: Programming Language :: Python :: 3.9
Classifier: Programming Language :: Python :: 3.10
Classifier: Programming Language :: Python :: 3.11
Classifier: Programming Language :: Python :: 3.12
Classifier: Programming Language :: Python :: 3.13
License-File: LICENSE
Dynamic: author
Dynamic: author-email
Dynamic: classifier
Dynamic: description
Dynamic: description-content-type
Dynamic: home-page
Dynamic: keywords
Dynamic: license
Dynamic: license-file
Dynamic: summary
